{
  "artist": {
    "master": {
      "name": "shintaro ono",
      "type": "middle of engineer_artist",
      "skills": [
        "notch",
        "touchdesigner"
      ],
      "image": "/image/artist/ono.png"
    },
    "member": [
      {
        "name": "koji azuma",
        "type": "collaborated photographer",
        "skills": [
          "sony α7rIII"
        ],
        "image": "/image/artist/aduma.png",
        "link": "https://kojiaduma.tumblr.com/"
      },
      {
        "name": "mieciaro",
        "type": "collaborated talent",
        "skills": [
          "model"
        ],
        "image": "/image/artist/mieciaro.png",
        "link": "https://kojiaduma.tumblr.com/"
      }
    ]
  }
}